setup.cfg
setup.py
hdat/__init__.py
hdat/casespec.py
hdat/hdat_cli.py
hdat/main.py
hdat/resultspec.py
hdat/runner.py
hdat/source_control.py
hdat/store.py
hdat/suite.py
hdat/util.py
hdat.egg-info/PKG-INFO
hdat.egg-info/SOURCES.txt
hdat.egg-info/dependency_links.txt
hdat.egg-info/entry_points.txt
hdat.egg-info/requires.txt
hdat.egg-info/top_level.txt