Metadata-Version: 1.1
Name: hdat
Version: 0.1.0
Summary: High Dimensional Algorithm Tester: A tool for manually verifying high-dimensionality algorithms.
Home-page: https://github.com/innolitics/hdat
Author: Innolitics, LLC
Author-email: info@innolitics.com
License: MIT
Keywords: scientific image
Platform: UNKNOWN
Classifier: Development Status :: 1 - Planning
Classifier: Intended Audience :: Developers
Classifier: Intended Audience :: Healthcare Industry
Classifier: Topic :: Software Development :: Build Tools
Classifier: Topic :: Scientific/Engineering :: Medical Science Apps.
Classifier: License :: OSI Approved :: MIT License
Classifier: Programming Language :: Python :: 3
Classifier: Programming Language :: Python :: 3.4
Classifier: Programming Language :: Python :: 3.5
Classifier: Programming Language :: Python :: 3.6
